swarmauri_certservice_ms_adcs/MsAdcsCertService.py
swarmauri_certservice_ms_adcs/__init__.py
swarmauri_certservice_ms_adcs-0.2.0.dev4.dist-info/LICENSE
swarmauri_certservice_ms_adcs-0.2.0.dev4.dist-info/METADATA
swarmauri_certservice_ms_adcs-0.2.0.dev4.dist-info/WHEEL
swarmauri_certservice_ms_adcs-0.2.0.dev4.dist-info/entry_points.txt
swarmauri_certservice_ms_adcs-0.2.0.dev4.dist-info/RECORD
