Metadata-Version: 2.3
Name: swarmauri_certservice_ms_adcs
Version: 0.2.0.dev4
Summary: Microsoft AD CS certificate service client for Swarmauri
License: Apache-2.0
Author: Swarmauri
Author-email: opensource@swarmauri.com
Requires-Python: >=3.10,<3.13
Classifier: License :: OSI Approved :: Apache Software License
Classifier: Programming Language :: Python :: 3.10
Classifier: Programming Language :: Python :: 3.11
Classifier: Programming Language :: Python :: 3.12
Provides-Extra: docs
Provides-Extra: kerberos
Provides-Extra: ntlm
Provides-Extra: perf
Requires-Dist: cryptography
Requires-Dist: mkdocs ; extra == "docs"
Requires-Dist: pytest-benchmark (>=4.0.0) ; extra == "perf"
Requires-Dist: requests (>=2.32.3)
Requires-Dist: requests-kerberos ; extra == "kerberos"
Requires-Dist: requests-ntlm ; extra == "ntlm"
Requires-Dist: swarmauri_base
Requires-Dist: swarmauri_core
Requires-Dist: swarmauri_standard
